Metadata-Version: 2.1
Name: odoo13-addon-sale-exception-financial-risk
Version: 13.0.1.0.1.dev3
Summary: Sale Exception financial_risk
Home-page: https://github.com/OCA/credit-control
Author: Tecnativa, Odoo Community Association (OCA)
Author-email: support@odoo-community.org
License: AGPL-3
Platform: UNKNOWN
Classifier: Programming Language :: Python
Classifier: Framework :: Odoo
Classifier: Framework :: Odoo :: 13.0
Classifier: License :: OSI Approved :: GNU Affero General Public License v3
Requires-Python: >=3.5
Requires-Dist: odoo13-addon-sale-exception
Requires-Dist: odoo13-addon-sale-financial-risk
Requires-Dist: odoo <13.1dev,>=13.0a
